spatial_polars/__init__.py
spatial_polars/_utils.py
spatial_polars/_vendor.py
spatial_polars/io.py
spatial_polars/spatialexpr.py
spatial_polars/spatialframe.py
spatial_polars/spatialseries.py
spatial_polars-0.2.3.dist-info/METADATA
spatial_polars-0.2.3.dist-info/WHEEL
spatial_polars-0.2.3.dist-info/entry_points.txt
spatial_polars-0.2.3.dist-info/licenses/LICENSE
spatial_polars-0.2.3.dist-info/RECORD
