Metadata-Version: 2.4
Name: spatial-polars
Version: 0.2.3
Summary: A package that extends polars for working with geospatial data.
Author-email: "Aaron T. Leese" <ATLeese@gmail.com>
License-File: LICENSE
Requires-Python: >=3.9
Requires-Dist: cloudpickle>=3.1.1
Requires-Dist: geoarrow-pyarrow>=0.1.2
Requires-Dist: numpy>=1.14
Requires-Dist: polars>=1.30.0
Requires-Dist: pyarrow>=14.0.2
Requires-Dist: pyogrio>=0.11.0
Requires-Dist: pyproj>=3.3
Requires-Dist: shapely>=2.0.7
Requires-Dist: tzdata>=2025.2
Provides-Extra: examples
Requires-Dist: geodatasets>=2024.8.0; extra == 'examples'
Provides-Extra: knn
Requires-Dist: scipy>=1.13.1; extra == 'knn'
Provides-Extra: lonboard
Requires-Dist: lonboard>=0.10.4; extra == 'lonboard'
Requires-Dist: matplotlib>=3.7.5; extra == 'lonboard'
Requires-Dist: palettable>=3.3.3; extra == 'lonboard'
